{
    "id": "2019-KR-04",
    "title": "Pantaloni adatti",
    "ages": {
        "0": "--",
        "1": "--",
        "2": "--",
        "3": "--",
        "4": "bonus",
        "5": "hard",
        "6-8": "--",
        "8-10": "--",
        "10-12": "--",
        "12-14": "--",
        "14-16": "bonus",
        "16-19": "hard"
    },
    "categories": [
        "algorithms and programming",
        "data structures and representations"
    ],
    "computational_thinking_skills": [],
    "answer_type": "multiple choice",
    "keywords": [],
    "support_files": [
        {
            "src": "*.svg by Kyra Willekes, adjusted by Susanne Datzko",
            "file_pattern": "*.svg",
            "authors": [
                "Kyra Willekes",
                "Susanne Datzko"
            ]
        }
    ],
    "contributors": [
        {
            "src": "Jihye Kim, anaki.csl@gmail.com, South Korea (author)",
            "name": "Jihye Kim",
            "country": "South Korea",
            "country_code": "KR",
            "roles": [
                "author"
            ],
            "email": "anaki.csl@gmail.com"
        },
        {
            "src": "Eslam AbdElAal, eslam@aast.edu, Egypt (contributor)",
            "name": "Eslam AbdElAal",
            "country": "Egypt",
            "country_code": "EG",
            "roles": [
                "contributor"
            ],
            "email": "eslam@aast.edu"
        },
        {
            "src": "Georgios Fesakis, gfesakis@aegean.gr, Greece (contributor)",
            "name": "Georgios Fesakis",
            "country": "Greece",
            "country_code": "GR",
            "roles": [
                "contributor"
            ],
            "email": "gfesakis@aegean.gr"
        },
        {
            "src": "Vipul Shah, v.shah@tcs.com, India (contributor)",
            "name": "Vipul Shah",
            "country": "India",
            "country_code": "IN",
            "roles": [
                "contributor"
            ],
            "email": "v.shah@tcs.com"
        },
        {
            "src": "Michael Weigend, mw@creative-informatics.de, Germany (contributor)",
            "name": "Michael Weigend",
            "country": "Germany",
            "country_code": "DE",
            "roles": [
                "contributor"
            ],
            "email": "mw@creative-informatics.de"
        },
        {
            "src": "Christian Datzko, christian@bebras.services, Hungary (contributor)",
            "name": "Christian Datzko",
            "country": "Hungary",
            "country_code": "HU",
            "roles": [
                "contributor"
            ],
            "email": "christian@bebras.services"
        },
        {
            "src": "Kyra Willekes, kwillekes@eljakim.nl, Netherlands (graphics)",
            "name": "Kyra Willekes",
            "country": "Netherlands",
            "country_code": "NL",
            "roles": [
                "graphics"
            ],
            "email": "kwillekes@eljakim.nl"
        },
        {
            "src": "Susanne Datzko, datzko@bwinf.ch, Germany (graphics)",
            "name": "Susanne Datzko",
            "country": "Germany",
            "country_code": "DE",
            "roles": [
                "graphics"
            ],
            "email": "datzko@bwinf.ch"
        },
        {
            "src": "Christian Giang, christian.giang@supsi.ch, Switzerland (translation from German into Italian)",
            "name": "Christian Giang",
            "country": "Switzerland",
            "country_code": "CH",
            "roles": [
                "translation from German into Italian"
            ],
            "email": "christian.giang@supsi.ch"
        }
    ],
    "equivalent_tasks": "--",
    "settings": {
        "default_image_scale": 0.4
    },
    "name": "Glass Slipper",
    "computer_science_areas": [
        "algorithms and programming",
        "data structures and representations"
    ],
    "difficulties": [
        0,
        0,
        0,
        0,
        4,
        3
    ],
    "lang_code": "ita",
    "lang": "Italian",
    "parsed_id": {
        "year": 2019,
        "country_code": "KR",
        "country": "South Korea",
        "num": 4
    }
}